{
  "version": "7",
  "dialect": "postgresql",
  "entries": [
    {
      "idx": 0,
      "version": "7",
      "when": 1769232518515,
      "tag": "0000_conscious_captain_universe",
      "breakpoints": true
    },
    {
      "idx": 1,
      "version": "7",
      "when": 1769399426410,
      "tag": "0001_thin_rocket_raccoon",
      "breakpoints": true
    },
    {
      "idx": 2,
      "version": "7",
      "when": 1769486400000,
      "tag": "0002_add_kid_profile_picture",
      "breakpoints": true
    }
  ]
}